CHANGES.rst
LICENSE.txt
MANIFEST.in
README.rst
requirements.txt
setup.py
views.py
views.egg-info/PKG-INFO
views.egg-info/SOURCES.txt
views.egg-info/dependency_links.txt
views.egg-info/top_level.txt