Metadata-Version: 1.1
Name: views
Version: 0.3
Summary: views
Home-page: https://github.com/k7hoven/views
Author: Koos Zevenhoven
Author-email: koos.zevenhoven@aalto.fi
License: BSD
Platform: UNKNOWN
Classifier: Development Status :: 3 - Alpha
Classifier: Natural Language :: English
Classifier: Operating System :: OS Independent
Classifier: Programming Language :: Python :: 3
